ssakg_extension.cpython-312-darwin.so
microrna/fasta_helper.py
microrna/mirna_encoder.py
microrna/mirna_example.py
microrna/ssakg_mirna_tester.py
sentences/gutenberg_sentences.py
sentences/sentences_coder.py
sentences/sentences_helper.py
sentences/sentences_memory.py
sentences/ssakg_sentences_tester.py
ssakg/__init__.py
ssakg/anakg.py
ssakg/anakg_view.py
ssakg/ordering_algorithms.py
ssakg/sequence_translator.py
ssakg/ssakg.py
ssakg/ssakg_extension.c
ssakg/subgraph_patterns.py
ssakg/utils/__init__.py
ssakg/utils/sequence_generator.py
ssakg/utils/ssakg_tester.py
tests/ssakg_example.py
tests/ssakg_test_example.py
ssakg-0.2.0.dist-info/LICENSE
ssakg-0.2.0.dist-info/METADATA
ssakg-0.2.0.dist-info/WHEEL
ssakg-0.2.0.dist-info/top_level.txt
ssakg-0.2.0.dist-info/RECORD
