Metadata-Version: 2.1
Name: ssakg
Version: 0.2.0
Summary: Sequential Structural Associative Knowledge Graph (ssakg)
Author-email: Przemysław Stokłosa <przemyslaw.stoklosa@gmail.com>
License: Apache 2.0
Project-URL: Homepage, https://github.com/PrzemyslawStok/ssakg
Keywords: semantic memory,structural graphs,graph density,sequence storage,sequence retrieval,context based memory,graph based memory,mirna sequences
Classifier: Development Status :: 4 - Beta
Classifier: Intended Audience :: Science/Research
Classifier: Programming Language :: Python :: 3
Classifier: License :: OSI Approved :: Apache Software License
Classifier: Operating System :: OS Independent
Requires-Python: <=3.12.7,>=3.10
License-File: LICENSE
Requires-Dist: numpy~=2.2.2
Requires-Dist: networkx~=3.2.1
Requires-Dist: matplotlib~=3.8.2
Requires-Dist: pandas~=2.2.0
Requires-Dist: tabulate~=0.9.0
Requires-Dist: PyPrind~=2.11.3
Requires-Dist: seaborn~=0.13.2
Provides-Extra: dev
Requires-Dist: numpy~=2.2.2; extra == "dev"
